[{"createdAt":"2021-04-24T22:16:51.546Z","feedId":"9f8d359a","uuid":"80e5","dislikers":[],"likers":[],"msg":"What did the late tomato say to the early tomato?\nI’ll ketch up","writer":{"uuid":"14ac","name":"Ethan"}},{"createdAt":"2021-04-24T22:16:51.852Z","feedId":"5b68e0e0","uuid":"440f","dislikers":[],"likers":[],"msg":"Why didn’t the orange win the race?\nIt ran out of juice.","writer":{"uuid":"14ac","name":"Ethan"}},{"createdAt":"2021-04-24T22:16:52.155Z","feedId":"bc277fbd","uuid":"9a9c","dislikers":[],"likers":[],"msg":"What's the difference between a seal and a sea lion?\nAn ion! ","writer":{"uuid":"14ac","name":"Ethan"}},{"createdAt":"2021-04-24T22:16:52.456Z","feedId":"4ca642a1","uuid":"dd65","dislikers":[],"likers":[],"msg":"A DHCP packet walks into a bar and asks for a beer.\nBartender says, \"here, but I’ll need that back in an hour!\"","writer":{"uuid":"14ac","name":"Ethan"}},{"createdAt":"2021-04-24T22:16:52.761Z","feedId":"1d687558","uuid":"4992","dislikers":[],"likers":[],"msg":"What do you call a troublesome Canadian high schooler?\nA poutine.","writer":{"uuid":"14ac","name":"Ethan"}}]